Metadata-Version: 2.1
Name: bags
Version: 0.4.0
Summary: Fast format for datasets.
Home-page: http://github.com/danijar/bags
Classifier: Intended Audience :: Science/Research
Classifier: License :: OSI Approved :: MIT License
Classifier: Programming Language :: Python :: 3
License-File: LICENSE
License-File: AUTHORS
